xswem/__init__.py
xswem/exceptions.py
xswem/model.py
xswem/utils.py
xswem-1.0.0.dist-info/LICENSE
xswem-1.0.0.dist-info/METADATA
xswem-1.0.0.dist-info/WHEEL
xswem-1.0.0.dist-info/top_level.txt
xswem-1.0.0.dist-info/RECORD
