Metadata-Version: 2.1
Name: xswem
Version: 1.0.0
Summary: A simple and explainable deep learning model for NLP.
Home-page: https://github.com/KieranLitschel/XSWEM
Author: Kieran Litschel
Author-email: kieran.litschel@outlook.com
License: MIT
Download-URL: https://github.com/KieranLitschel/XSWEM/tags
Keywords: nlp fast machine learning deep simple tensorflow model word embeddings keras glove explainable swem global local explanations
Platform: UNKNOWN
Classifier: Programming Language :: Python :: 3
Classifier: License :: OSI Approved :: MIT License
Classifier: Operating System :: OS Independent
Classifier: Topic :: Scientific/Engineering :: Artificial Intelligence
Requires-Python: >=3.6
Requires-Dist: tensorflow (>=2.0.0)
Requires-Dist: pandas
Requires-Dist: numpy (>=1.16.5)
Requires-Dist: seaborn
Requires-Dist: matplotlib
Requires-Dist: tqdm
